drf_ujson/__init__.py
drf_ujson/parsers.py
drf_ujson/renderers.py
drf_ujson2-1.8.0.dist-info/LICENSE
drf_ujson2-1.8.0.dist-info/METADATA
drf_ujson2-1.8.0.dist-info/WHEEL
drf_ujson2-1.8.0.dist-info/top_level.txt
drf_ujson2-1.8.0.dist-info/RECORD
