Metadata-Version: 2.1
Name: drf-ujson2
Version: 1.8.0
Summary: Django Rest Framework UJSON Renderer
Home-page: https://github.com/Amertz08/drf_ujson2
Author: Gizmag
Author-email: tech@gizmag.com
Keywords: django,djangorestframework,ujson
Classifier: Development Status :: 5 - Production/Stable
Classifier: Programming Language :: Python :: 3.10
Classifier: Programming Language :: Python :: 3.11
Classifier: Programming Language :: Python :: 3.12
Classifier: Programming Language :: Python :: 3.13
Classifier: Framework :: Django :: 4.2
Classifier: Framework :: Django :: 5.0
Classifier: Framework :: Django :: 5.1
Classifier: Intended Audience :: Developers
Classifier: License :: OSI Approved :: MIT License
Requires-Python: >=3.10
License-File: LICENSE
Requires-Dist: django
Requires-Dist: ujson >=4.2.0
Requires-Dist: djangorestframework
Provides-Extra: dev
Requires-Dist: pytest ; extra == 'dev'
Requires-Dist: pytest-django ; extra == 'dev'
Requires-Dist: pytest-cov ; extra == 'dev'
Requires-Dist: pytest-mock ; extra == 'dev'
